{
  "auth": {
    "amplifyapp0bbfb25d": {
      "service": "Cognito",
      "providerPlugin": "awscloudformation",
      "dependsOn": [],
      "customAuth": false
    }
  },
  "api": {
    "notesapp": {
      "service": "AppSync",
      "providerPlugin": "awscloudformation",
      "output": {
        "authConfig": {
          "defaultAuthentication": {
            "authenticationType": "API_KEY",
            "apiKeyConfig": {
              "apiKeyExpirationDays": 7,
              "description": "demo"
            }
          },
          "additionalAuthenticationProviders": []
        }
      }
    }
  },
  "storage": {
    "imagestorage": {
      "service": "S3",
      "providerPlugin": "awscloudformation"
    }
  },
  "function": {
    "amplifyappapi": {
      "build": true,
      "providerPlugin": "awscloudformation",
      "service": "Lambda",
      "dependsOn": [
        {
          "category": "auth",
          "resourceName": "amplifyapp0bbfb25d",
          "attributes": [
            "UserPoolId"
          ]
        },
        {
          "category": "api",
          "resourceName": "notesapp",
          "attributes": [
            "GraphQLAPIIdOutput",
            "GraphQLAPIEndpointOutput",
            "GraphQLAPIKeyOutput"
          ]
        },
        {
          "category": "storage",
          "resourceName": "imagestorage",
          "attributes": [
            "BucketName"
          ]
        }
      ]
    }
  },
  "hosting": {
    "amplifyhosting": {
      "service": "amplifyhosting",
      "providerPlugin": "awscloudformation",
      "type": "manual"
    }
  }
}